{
	"class" : {
		"initializePossibleConnected" : "bliznjan 5/11/2015 16:28:42",
		"isPossibleIncoming:" : "bliznjan 5/11/2015 16:28:42",
		"isPossibleOutgoing:" : "bliznjan 5/11/2015 16:28:42" },
	"instance" : {
		"addAsSourceFor:" : "bliznjan 5/11/2015 16:28:42",
		"addAsTargetFor:" : "bliznjan 5/11/2015 16:28:42",
		"canBeSourceFor:" : "bliznjan 5/11/2015 16:28:42",
		"canBeTargetFor:" : "bliznjan 5/11/2015 16:28:42",
		"createFigure" : "bliznjan 5/11/2015 16:28:42",
		"createRoassalShape" : "bliznjan 5/11/2015 16:28:42",
		"refreshFigure" : "bliznjan 5/11/2015 16:28:42",
		"sameKindAs:" : "bliznjan 5/11/2015 16:28:42" } }
